precice_config_graph/edges.py
precice_config_graph/enums.py
precice_config_graph/graph.py
precice_config_graph/nodes.py
precice_config_graph/xml_processing.py
precice_config_graph-2.0.5.dist-info/licenses/LICENSE
precice_config_graph-2.0.5.dist-info/METADATA
precice_config_graph-2.0.5.dist-info/WHEEL
precice_config_graph-2.0.5.dist-info/top_level.txt
precice_config_graph-2.0.5.dist-info/RECORD
