Metadata-Version: 2.4
Name: precice-config-graph
Version: 2.0.5
Summary: A Library that builds a graph from a preCICE configuration file for validation and visualization purposes
License-Expression: MIT
Project-URL: Repository, https://github.com/precice/config-graph.git
Requires-Python: >=3.10
License-File: LICENSE
Requires-Dist: lxml
Requires-Dist: elementpath
Requires-Dist: matplotlib
Requires-Dist: networkx
Requires-Dist: pytest
Dynamic: license-file
